gridstatusio/__init__.py
gridstatusio/gs_client.py
gridstatusio/utils.py
gridstatusio/version.py
gridstatusio/tests/__init__.py
gridstatusio/tests/test_api.py
gridstatusio/tests/test_retries.py
gridstatusio/tests/test_timezone_behavior.py
gridstatusio/tests/test_version.py
gridstatusio-0.15.1.dist-info/METADATA
gridstatusio-0.15.1.dist-info/WHEEL
gridstatusio-0.15.1.dist-info/licenses/LICENSE
gridstatusio-0.15.1.dist-info/RECORD
