Metadata-Version: 2.4
Name: gridstatusio
Version: 0.15.1
Summary: Python Client for GridStatus.io API
Project-URL: Source Code, https://github.com/kmax12/gridstatusio/
Project-URL: Issue Tracker, https://github.com/kmax12/gridstatusio/issues
Author-email: Max Kanter <kmax12@gmail.com>
Maintainer-email: Max Kanter <kmax12@gmail.com>
License: Copyright 2022 James Max Kanter
License-File: LICENSE
Keywords: energy,independent system operator
Classifier: Programming Language :: Python
Classifier: Programming Language :: Python :: 3
Classifier: Programming Language :: Python :: 3.10
Classifier: Programming Language :: Python :: 3.11
Classifier: Programming Language :: Python :: 3.12
Classifier: Programming Language :: Python :: 3.13
Requires-Python: <4,>=3.10
Requires-Dist: certifi<2025,>=2024.7.4
Requires-Dist: idna~=3.7
Requires-Dist: ipykernel>=6.30.0
Requires-Dist: numpy<2,>=1.26.4
Requires-Dist: pandas>=2.3.0
Requires-Dist: plotly>=5.20.0
Requires-Dist: requests<3,>=2.32.2
Requires-Dist: setuptools<81,>=70.0.0
Requires-Dist: tabulate<0.10,>=0.9.0
Requires-Dist: termcolor>=3.2.0
Requires-Dist: tqdm<5,>=4.66.3
Requires-Dist: urllib3<3,>=2.2.2
Requires-Dist: virtualenv<21,>=20.26.6
